doit_watch/__init__.py
doit_watch/cmd_watch.py
doit_watch/filewatch.py
doit_watch-0.1.0.dist-info/LICENSE
doit_watch-0.1.0.dist-info/METADATA
doit_watch-0.1.0.dist-info/WHEEL
doit_watch-0.1.0.dist-info/RECORD
